{
  "options" : {
    "keyboardBaseUri" : "https://raw.githubusercontent.com/jmeberlein/OldEnglishKeyboard/master/",
    "fontBaseUri" : "https://raw.githubusercontent.com/jmeberlein/OldEnglishKeyboard/master/"
  },
  "keyboard" : {
    "id" : "aenglisc",
    "name" : "\u00C6nglisc",
    "filename" : "aenglisc-1.0.js",
    "version" : "1.0",
    "lastModified" : "2017-05-05T15:24:56.024-05:00",
    "languages" : [
      {
        "id" : "ang",
        "name" : "Old English"
      }
      ]
  }
}
